djunk/__init__.py
djunk/apps/__init__.py
djunk/apps/core/__init__.py
djunk/apps/core/apps.py
djunk/apps/core/management/__init__.py
djunk/apps/core/management/commands/__init__.py
djunk/apps/core/management/commands/app_template/__init__.py-tpl
djunk/apps/core/management/commands/app_template/admin.py-tpl
djunk/apps/core/management/commands/app_template/apps.py-tpl
djunk/apps/core/management/commands/app_template/factories.py-tpl
djunk/apps/core/management/commands/app_template/migrations/__init__.py-tpl
djunk/apps/core/management/commands/app_template/models.py-tpl
djunk/apps/core/management/commands/app_template/tests/__init__.py-tpl
djunk/apps/core/management/commands/app_template/tests/conftest.py-tpl
djunk/apps/core/management/commands/initapp.py
djunk/apps/core/tests/__init__.py
djunk/apps/core/tests/test_core.py
djunk/apps/templating/__init__.py
djunk/apps/templating/apps.py
djunk/apps/templating/templates/templating/cart.html
djunk/apps/templating/templates/templating/misc.html
djunk/apps/templating/templatetags/__init__.py
djunk/apps/templating/templatetags/expr.py
djunk/apps/templating/tests/__init__.py
djunk/apps/templating/tests/conftest.py
djunk/apps/templating/tests/test_expr.py
djunk/apps/templating/types.py
djunk/apps/templating/utils.py
djunk/asgi.py
djunk/py.typed
djunk/settings/__init__.py
djunk/settings/base.py
djunk/settings/local_example.py
djunk/urls.py
djunk/wsgi.py
djunk-0.2.0.dist-info/LICENSE
djunk-0.2.0.dist-info/WHEEL
djunk-0.2.0.dist-info/METADATA
djunk-0.2.0.dist-info/RECORD
