Metadata-Version: 2.1
Name: djunk
Version: 0.2.0
Summary: My personal 'junk drawer' of reusable Django apps and related snippets.
License: MIT
Author: Jordan Eremieff
Author-email: jordan@eremieff.com
Requires-Python: >=3.10,<4.0
Classifier: License :: OSI Approved :: MIT License
Classifier: Programming Language :: Python :: 3
Classifier: Programming Language :: Python :: 3.10
Requires-Dist: Django (>=4.0.4,<5.0.0)
